source_posthog/__init__.py
source_posthog/components.py
source_posthog/manifest.yaml
source_posthog/run.py
source_posthog/schemas/annotations.json
source_posthog/schemas/cohorts.json
source_posthog/schemas/events.json
source_posthog/schemas/feature_flags.json
source_posthog/schemas/insights.json
source_posthog/schemas/persons.json
source_posthog/schemas/projects.json
source_posthog/source.py
source_posthog/spec.json
airbyte_source_posthog-1.1.25.dist-info/METADATA
airbyte_source_posthog-1.1.25.dist-info/WHEEL
airbyte_source_posthog-1.1.25.dist-info/entry_points.txt
airbyte_source_posthog-1.1.25.dist-info/RECORD
